wlabkit/__init__.py
wlabkit/exsl_seq.py
wlabkit/get_seq_header.py
wlabkit/getseq.py
wlabkit/parse_antismash_html.py
wlabkit/parse_antismash_result.py
wlabkit/parse_gbk.py
wlabkit-0.8.0.data/scripts/wlabkit
wlabkit-0.8.0.dist-info/LICENSE
wlabkit-0.8.0.dist-info/METADATA
wlabkit-0.8.0.dist-info/WHEEL
wlabkit-0.8.0.dist-info/top_level.txt
wlabkit-0.8.0.dist-info/RECORD
