Metadata-Version: 2.1
Name: wlabkit
Version: 0.8.0
Summary: A toolkit to handle bio-data from WeiBin Lab.
Home-page: https://github.com/BioGavin/wlab
Author: Zhen-Yi Zhou
Author-email: gavinchou64@gmail.com
License: GPL
Classifier: Programming Language :: Python :: 3.8
Classifier: License :: OSI Approved :: GNU General Public License v3 (GPLv3)
Classifier: Operating System :: OS Independent
Requires-Python: >=3.8
License-File: LICENSE
Requires-Dist: biopython
Requires-Dist: numpy
Requires-Dist: pandas
Requires-Dist: python-dateutil
Requires-Dist: pytz
Requires-Dist: six
